datatables/__init__.py
datatables/contract.py
datatables/core.py
datatables/database.py
datatables/exceptions.py
datatables/schema.py
datatables/utils.py
fp_datatables-0.1.2.dist-info/METADATA
fp_datatables-0.1.2.dist-info/WHEEL
fp_datatables-0.1.2.dist-info/top_level.txt
fp_datatables-0.1.2.dist-info/RECORD
