Metadata-Version: 2.4
Name: fp-datatables
Version: 0.1.2
Summary: Add your description here
License: MIT
Project-URL: Homepage, https://github.com/Rohit-kumar-raja/fastapi-datatables
Requires-Python: >=3.12
Requires-Dist: pydantic>=2.11.9
Requires-Dist: sqlalchemy>=2.0.43
